actualcauses/__init__.py
actualcauses/isi.py
actualcauses/lucb.py
actualcauses/mbs.py
actualcauses/scm.py
actualcauses/system_model.py
actualcauses-1.0.1.dist-info/licenses/LICENSE
actualcauses-1.0.1.dist-info/METADATA
actualcauses-1.0.1.dist-info/WHEEL
actualcauses-1.0.1.dist-info/top_level.txt
actualcauses-1.0.1.dist-info/RECORD
