Metadata-Version: 2.4
Name: actualcauses
Version: 1.0.1
Summary: A package for Actual Causes Identification
Home-page: https://github.com/SamuelReyd/ActualCausesIdentification
Author: Samuel Reyd
Author-email: samuelreyd@gmail.com
License: MIT
Project-URL: Homepage, https://github.com/SamuelReyd/ActualCausesIdentification
Project-URL: Repository, https://github.com/SamuelReyd/ActualCausesIdentification
Project-URL: Issues, https://github.com/SamuelReyd/ActualCausesIdentification/issues
Keywords: causality,actual causation,explainability,SCM,Halpern-Pearl causes,causes identification,counterfactual reasoning
Classifier: License :: OSI Approved :: MIT License
Classifier: Programming Language :: Python :: 3
Classifier: Programming Language :: Python :: 3 :: Only
Requires-Python: >=3.9
License-File: LICENSE
Requires-Dist: tqdm>=4.62.3
Requires-Dist: numpy>=1.21.0
Provides-Extra: dev
Requires-Dist: pytest>=7; extra == "dev"
Requires-Dist: ruff>=0.5; extra == "dev"
Requires-Dist: build>=1.2; extra == "dev"
Requires-Dist: twine>=5; extra == "dev"
Dynamic: author-email
Dynamic: home-page
Dynamic: license-file
